{
  "Python": {
    "what is python": "Python is a high-level, interpreted programming language known for readability, simplicity, and versatility, used in web development, data science, AI, and scripting.",
    "what are python data types": "Python data types include int, float, str, bool, list, tuple, set, and dict, each used to store different kinds of values.",
    "what is python list": "A list is an ordered, mutable collection of items in Python, allowing duplicates and indexed access.",
    "what is python tuple": "A tuple is an ordered, immutable collection of items in Python, useful for fixed data.",
    "what is python set": "A set is an unordered collection of unique items, used for membership testing and removing duplicates.",
    "what is python dictionary": "A dictionary is a key-value collection in Python, allowing fast access to data via keys.",
    "what is python variable": "A variable stores data values in memory, and Python variables are dynamically typed.",
    "what is python function": "A function is a reusable block of code in Python that performs a specific task and can return a value.",
    "what is python class": "A class is a blueprint for creating objects in Python, supporting encapsulation and object-oriented programming.",
    "what is python object": "An object is an instance of a class containing data (attributes) and behavior (methods).",
    "what is python module": "A module is a file containing Python definitions and functions, which can be imported into other programs.",
    "what is python package": "A package is a collection of Python modules organized in directories with an __init__.py file.",
    "what is python list comprehension": "List comprehension is a concise way to create lists using a single line with loops and conditions.",
    "what is python lambda function": "A lambda function is an anonymous, inline function defined with the lambda keyword.",
    "what is python decorator": "A decorator is a function that modifies the behavior of another function or method without changing its code.",
    "what is python iterator": "An iterator is an object that allows traversal through all elements of a collection one at a time.",
    "what is python generator": "A generator is an iterator that yields values lazily using the 'yield' keyword, saving memory for large datasets.",
    "what is python comprehension": "Comprehensions (list, set, dict) provide a concise way to create collections in Python using loops and conditions.",
    "what is python string": "A string is an ordered sequence of characters used to store and manipulate text data.",
    "what is python slicing": "Slicing extracts a portion of a sequence like a list, tuple, or string using start, stop, and step indices.",
    "what is python indexing": "Indexing accesses individual elements of sequences using integer positions, starting at 0.",
    "what is python if statement": "The if statement executes a block of code conditionally based on a boolean expression.",
    "what is python elif": "Elif allows multiple conditional checks after an if statement before the else block.",
    "what is python else": "Else provides a block of code executed when previous conditions in if or elif are False.",
    "what is python for loop": "For loop iterates over items of a sequence or iterable, executing a block of code for each item.",
    "what is python while loop": "While loop executes a block of code repeatedly as long as a condition remains True.",
    "what is python break": "Break exits the nearest enclosing loop immediately, skipping remaining iterations.",
    "what is python continue": "Continue skips the current iteration of a loop and proceeds to the next iteration.",
    "what is python pass": "Pass is a null statement used as a placeholder where syntactic code is required but no action is needed.",
    "what is python exception handling": "Exception handling in Python uses try, except, finally to manage runtime errors and ensure program stability.",
    "what is python try block": "The try block contains code that may raise an exception, which is handled by except blocks.",
    "what is python except block": "Except block catches and handles exceptions raised in the try block.",
    "what is python finally block": "Finally block executes code regardless of whether an exception occurred, often used for cleanup.",
    "what is python raise statement": "Raise explicitly throws an exception in Python to signal errors or invalid conditions.",
    "what is python assert statement": "Assert checks a condition during execution and raises an AssertionError if the condition is False.",
    "what is python import statement": "Import allows using modules and packages in Python code to access functions, classes, or variables.",
    "what is python from import": "From-import allows importing specific attributes from a module instead of the whole module.",
    "what is python pip": "Pip is the package manager for Python used to install, update, and manage third-party packages.",
    "what is python virtual environment": "A virtual environment isolates Python projects with their dependencies, preventing conflicts between packages.",
    "what is python os module": "The os module provides functions to interact with the operating system like file management and environment variables.",
    "what is python sys module": "The sys module provides access to system-specific parameters and functions, such as command-line arguments.",
    "what is python math module": "The math module offers mathematical functions like sin, cos, sqrt, factorial, and constants like pi.",
    "what is python random module": "The random module provides functions to generate random numbers, select random items, and shuffle sequences.",
    "what is python datetime module": "The datetime module handles dates and times, allowing operations like formatting, arithmetic, and comparison.",
    "what is python file handling": "File handling allows reading, writing, and manipulating files using open, read, write, and close functions.",
    "what is python with statement": "The with statement simplifies file handling by automatically closing files after operations, ensuring resource management.",
    "what is python read function": "Read function reads content from a file, either entirely or by specifying the number of characters.",
    "what is python readline function": "Readline reads a single line from a file, moving the file pointer to the next line.",
    "what is python readlines function": "Readlines reads all lines from a file and returns a list of strings.",
    "what is python write function": "Write writes content to a file, overwriting existing data or appending based on mode.",
    "what is python append mode": "Append mode adds new content to the end of a file without removing existing data.",
    "what is python open modes": "Open modes define how files are accessed: 'r' for read, 'w' for write, 'a' for append, 'rb'/'wb' for binary files.",
    "what is python exception types": "Python exceptions include ValueError, TypeError, KeyError, IndexError, FileNotFoundError, and ZeroDivisionError.",
    "what is python dir function": "Dir returns a list of valid attributes and methods of an object or module.",
    "what is python help function": "Help displays the documentation of modules, classes, functions, and objects.",
    "what is python type function": "Type returns the data type of an object in Python.",
    "what is python isinstance function": "Isinstance checks if an object is an instance of a specified class or type.",
    "what is python id function": "Id returns the unique memory address of an object.",
    "what is python input function": "Input reads user input from the console and returns it as a string.",
    "what is python print function": "Print outputs data to the console, supporting multiple arguments and formatting.",
    "what is python string formatting": "String formatting inserts variables into strings using f-strings, format(), or % operator.",
    "what is python string methods": "Common string methods include upper(), lower(), strip(), split(), join(), replace(), find(), and count().",
    "what is python list methods": "List methods include append(), extend(), insert(), remove(), pop(), clear(), index(), count(), sort(), and reverse().",
    "what is python dictionary methods": "Dictionary methods include keys(), values(), items(), get(), update(), pop(), popitem(), and clear().",
    "what is python set methods": "Set methods include add(), remove(), discard(), union(), intersection(), difference(), and symmetric_difference().",
    "what is python tuple methods": "Tuples have limited methods like count() and index() due to immutability.",
    "what is python comprehensions": "Python comprehensions create lists, sets, or dictionaries concisely using loops and conditions.",
    "what is python map function": "Map applies a function to all items of an iterable and returns a map object.",
    "what is python filter function": "Filter selects items from an iterable based on a function returning True or False.",
    "what is python reduce function": "Reduce applies a function cumulatively to items of an iterable, returning a single value.",
    "what is python zip function": "Zip combines multiple iterables element-wise into tuples.",
    "what is python enumerate function": "Enumerate adds a counter to an iterable, returning pairs of index and item.",
    "what is python globals function": "Globals returns a dictionary of global variables in the current module.",
    "what is python locals function": "Locals returns a dictionary of local variables in the current scope.",
    "what is python eval function": "Eval executes a string as a Python expression and returns the result.",
    "what is python exec function": "Exec executes dynamically created Python code from strings or code objects.",
    "what is python garbage collection": "Python garbage collection automatically manages memory by deleting unreachable objects.",
    "what is python shallow copy": "Shallow copy duplicates an object without copying nested objects, sharing references.",
    "what is python deep copy": "Deep copy duplicates an object and all objects it contains, creating independent copies.",
    "what is python multithreading": "Multithreading allows multiple threads to run concurrently in a single process for I/O tasks.",
    "what is python multiprocessing": "Multiprocessing runs separate processes in parallel to utilize multiple CPU cores for computation-heavy tasks.",
    "what is python asyncio": "Asyncio provides asynchronous I/O using async/await, enabling non-blocking operations."
  }
}
